LICENSE.md
MANIFEST.in
README.md
setup.cfg
setup.py
rest_channels/__init__.py
rest_channels/exceptions.py
rest_channels/models.py
rest_channels/parsers.py
rest_channels/renderers.py
rest_channels/settings.py
rest_channels/socket_request.py
rest_channels/views.py
rest_channels.egg-info/PKG-INFO
rest_channels.egg-info/SOURCES.txt
rest_channels.egg-info/dependency_links.txt
rest_channels.egg-info/requires.txt
rest_channels.egg-info/top_level.txt
rest_channels/migrations/__init__.py
rest_channels/socket_routing/__init__.py
rest_channels/socket_routing/decorators.py
rest_channels/socket_routing/route_views.py
rest_channels/socket_routing/serializers.py
rest_channels/tests/__init__.py
rest_channels/tests/settings.py