Metadata-Version: 1.1
Name: rest-channels
Version: 0.1.3
Summary: Class Based Views for Django Channels with Django Rest Framework
Home-page: https://github.com/KhasanovBI/rest_channels
Author: Khasanov Bulat
Author-email: afti@yandex.ru
License: BSD License
Platform: UNKNOWN
Classifier: Environment :: Web Environment
Classifier: Framework :: Django
Classifier: Intended Audience :: Developers
Classifier: License :: OSI Approved :: BSD License
Classifier: Operating System :: OS Independent
Classifier: Programming Language :: Python
Classifier: Programming Language :: Python :: 2.7
Classifier: Programming Language :: Python :: 3.4
Classifier: Programming Language :: Python :: 3.5
Classifier: Programming Language :: Python :: 3.6
Classifier: Topic :: Internet :: WWW/HTTP
